claude_agent_sdk/__init__.py
claude_agent_sdk/_cli_version.py
claude_agent_sdk/_errors.py
claude_agent_sdk/_version.py
claude_agent_sdk/client.py
claude_agent_sdk/py.typed
claude_agent_sdk/query.py
claude_agent_sdk/types.py
claude_agent_sdk/_bundled/.gitignore
claude_agent_sdk/_bundled/claude
claude_agent_sdk/_internal/__init__.py
claude_agent_sdk/_internal/client.py
claude_agent_sdk/_internal/message_parser.py
claude_agent_sdk/_internal/query.py
claude_agent_sdk/_internal/transport/__init__.py
claude_agent_sdk/_internal/transport/subprocess_cli.py
claude_agent_sdk-0.1.27.dist-info/METADATA
claude_agent_sdk-0.1.27.dist-info/WHEEL
claude_agent_sdk-0.1.27.dist-info/licenses/LICENSE
claude_agent_sdk-0.1.27.dist-info/RECORD
