Metadata-Version: 2.4
Name: claude-agent-sdk
Version: 0.1.27
Summary: Python SDK for Claude Code
Project-URL: Homepage, https://github.com/anthropics/claude-agent-sdk-python
Project-URL: Documentation, https://docs.anthropic.com/en/docs/claude-code/sdk
Project-URL: Issues, https://github.com/anthropics/claude-agent-sdk-python/issues
Author-email: Anthropic <support@anthropic.com>
License: MIT
License-File: LICENSE
Keywords: ai,anthropic,claude,sdk
Classifier: Development Status :: 3 - Alpha
Classifier: Intended Audience :: Developers
Classifier: License :: OSI Approved :: MIT License
Classifier: Programming Language :: Python :: 3
Classifier: Programming Language :: Python :: 3.10
Classifier: Programming Language :: Python :: 3.11
Classifier: Programming Language :: Python :: 3.12
Classifier: Programming Language :: Python :: 3.13
Classifier: Typing :: Typed
Requires-Python: >=3.10
Requires-Dist: anyio>=4.0.0
Requires-Dist: mcp>=0.1.0
Requires-Dist: typing-extensions>=4.0.0; python_version < '3.11'
Provides-Extra: dev
Requires-Dist: anyio[trio]>=4.0.0; extra == 'dev'
Requires-Dist: mypy>=1.0.0; extra == 'dev'
Requires-Dist: pytest-asyncio>=0.20.0; extra == 'dev'
Requires-Dist: pytest-cov>=4.0.0; extra == 'dev'
Requires-Dist: pytest>=7.0.0; extra == 'dev'
Requires-Dist: ruff>=0.1.0; extra == 'dev'
